MANIFEST.in
README.md
setup.py
telemetron_client.egg-info/PKG-INFO
telemetron_client.egg-info/SOURCES.txt
telemetron_client.egg-info/dependency_links.txt
telemetron_client.egg-info/not-zip-safe
telemetron_client.egg-info/requires.txt
telemetron_client.egg-info/top_level.txt
telemetronclient/__init__.py
telemetronclient/defaults.py
telemetronclient/exceptions.py
telemetronclient/telemetronclient.py
telemetronclient/utils/__init__.py
telemetronclient/utils/deepdict.py
telemetronclient/utils/dryrunner.py
telemetronclient/utils/map.py
tests/__init__.py
tests/functional_tests/__init__.py
tests/functional_tests/helpers.py
tests/functional_tests/test_telemetronclient.py
tests/unit_tests/__init__.py
tests/unit_tests/test_deepdict.py
tests/unit_tests/test_map.py
tests/unit_tests/test_telemetronclient.py