Metadata-Version: 1.0
Name: telemetron-client
Version: 4.0.0
Summary: Client for Telemetron
Home-page: https://bitbucket.org/mindera/telemetry-client-python
Author: Joao Coutinho
Author-email: joao.coutinho@mindera.com
License: UNKNOWN
Platform: UNKNOWN
